genuine/__init__.py
genuine/bases.py
genuine/py.typed
genuine/stubs.py
genuine-0.2.0.dist-info/LICENSE
genuine-0.2.0.dist-info/METADATA
genuine-0.2.0.dist-info/WHEEL
genuine-0.2.0.dist-info/RECORD
