Metadata-Version: 2.1
Name: genuine
Version: 0.2.0
Summary: Genuine makes it easy to create test data and associations.
Home-page: https://johnnoone.github.io/genuine/
License: BSD-3-Clause
Keywords: tests,fixtures
Author: Xavier Barbosa
Author-email: clint.northwood@gmail.com
Requires-Python: >=3.11,<4.0
Classifier: License :: OSI Approved :: BSD License
Classifier: Programming Language :: Python :: 3
Classifier: Programming Language :: Python :: 3.11
Classifier: Programming Language :: Python :: 3.12
Classifier: Programming Language :: Python :: 3.13
Classifier: Topic :: Software Development :: Libraries :: Python Modules
Classifier: Topic :: Software Development :: Testing
Requires-Dist: typing-extensions (>=4.8.0)
Project-URL: Repository, https://github.com/johnnoone/genuine
